jira_offline/__init__.py
jira_offline/auth.py
jira_offline/config.py
jira_offline/create.py
jira_offline/exceptions.py
jira_offline/jira.py
jira_offline/linters.py
jira_offline/models.py
jira_offline/sql_filter.py
jira_offline/sync.py
jira_offline/cli/__init__.py
jira_offline/cli/linters.py
jira_offline/cli/main.py
jira_offline/cli/params.py
jira_offline/cli/stats.py
jira_offline/utils/__init__.py
jira_offline/utils/api.py
jira_offline/utils/cli.py
jira_offline/utils/convert.py
jira_offline/utils/decorators.py
jira_offline/utils/serializer.py
jira_offline-0.2.5.dist-info/LICENSE
jira_offline-0.2.5.dist-info/METADATA
jira_offline-0.2.5.dist-info/WHEEL
jira_offline-0.2.5.dist-info/entry_points.txt
jira_offline-0.2.5.dist-info/top_level.txt
jira_offline-0.2.5.dist-info/RECORD
