Metadata-Version: 2.1
Name: jira-offline
Version: 0.2.5
Summary: CLI for using Jira offline
Home-page: http://github.com/mafrosis/jira-offline
Author: Matt Black
Author-email: dev@mafro.net
License: MIT License
Platform: UNKNOWN
Classifier: Development Status :: 5 - Production/Stable
Classifier: Environment :: Console
Classifier: Intended Audience :: Developers
Classifier: Intended Audience :: System Administrators
Classifier: Natural Language :: English
Classifier: License :: OSI Approved :: MIT License
Classifier: Programming Language :: Python
Classifier: Programming Language :: Python :: 3.6
Classifier: Programming Language :: Python :: 3.7
Classifier: Programming Language :: Python :: 3.8
License-File: LICENSE
Requires-Dist: arrow (==0.15.8)
Requires-Dist: click (==8.0.1)
Requires-Dist: cryptography (==3.4.7)
Requires-Dist: dictdiffer-jira-offline-fork (==0.0.1)
Requires-Dist: pyarrow (==3.0.0)
Requires-Dist: feather-format (==0.4.1)
Requires-Dist: moz-sql-parser (==4.21.21059)
Requires-Dist: oauthlib (==3.1.0)
Requires-Dist: ProxyTypes (==0.10.0)
Requires-Dist: requests (==2.25.1)
Requires-Dist: requests-oauthlib (==1.3.0)
Requires-Dist: tabulate (==0.8.9)
Requires-Dist: tqdm (==4.49.0)
Requires-Dist: typing-inspect (==0.6.0)
Requires-Dist: tzlocal (==2.1)
Requires-Dist: dataclasses ; python_version <= "3.6"
Requires-Dist: typing ; python_version <= "3.6"
Requires-Dist: numpy (==1.19.5) ; python_version == "3.6"
Requires-Dist: pandas (==1.1.5) ; python_version == "3.6"
Requires-Dist: numpy (==1.20.1) ; python_version >= "3.7"
Requires-Dist: pandas (==1.2.3) ; python_version >= "3.7"
